{
  "indexes": [
    {
      "collectionGroup": "stories",
      "queryScope": "COLLECTION",
      "fields": [
        { "fieldPath": "userId", "order": "ASCENDING" },
        { "fieldPath": "expiresAt", "order": "DESCENDING" }
      ]
    },
    {
      "collectionGroup": "stories",
      "queryScope": "COLLECTION",
      "fields": [
        { "fieldPath": "userId", "order": "ASCENDING" },
        { "fieldPath": "isDeleted", "order": "ASCENDING" },
        { "fieldPath": "expiresAt", "order": "DESCENDING" }
      ]
    },
    {
      "collectionGroup": "chats",
      "queryScope": "COLLECTION",
      "fields": [
        { "fieldPath": "participantIds", "arrayConfig": "CONTAINS" },
        { "fieldPath": "isAiChat", "order": "ASCENDING" },
        { "fieldPath": "lastMessageAt", "order": "DESCENDING" }
      ]
    },
    {
      "collectionGroup": "messages",
      "queryScope": "COLLECTION",
      "fields": [
        { "fieldPath": "chatId", "order": "ASCENDING" },
        { "fieldPath": "createdAt", "order": "DESCENDING" }
      ]
    },
    {
      "collectionGroup": "ai_logs",
      "queryScope": "COLLECTION",
      "fields": [
        { "fieldPath": "userId", "order": "ASCENDING" },
        { "fieldPath": "timestamp", "order": "DESCENDING" }
      ]
    },
    {
      "collectionGroup": "support",
      "queryScope": "COLLECTION",
      "fields": [
        { "fieldPath": "userId", "order": "ASCENDING" },
        { "fieldPath": "createdAt", "order": "DESCENDING" }
      ]
    }
  ],
  "fieldOverrides": []
}